mail_ops_scripts-2.5.1.dist-info/licenses/LICENSE
mailops/__init__.py
mailops/__main__.py
mailops/blacklist_monitor.py
mailops/cli.py
mailops/dkim_gen.py
mailops/dmarc_parser.py
mailops/imap_fetcher.py
mailops/spf_check.py
mailops/ui.py
mail_ops_scripts-2.5.1.dist-info/METADATA
mail_ops_scripts-2.5.1.dist-info/WHEEL
mail_ops_scripts-2.5.1.dist-info/entry_points.txt
mail_ops_scripts-2.5.1.dist-info/top_level.txt
mail_ops_scripts-2.5.1.dist-info/RECORD
