Metadata-Version: 2.4
Name: mail-ops-scripts
Version: 2.5.1
Summary: A unified operational toolkit for email server administration and DMARC analysis.
Author-email: Beau Bremer <beau.bremer@tutamial.com>
License: MIT
Project-URL: Homepage, https://github.com/KnowOneActual/mail-ops-scripts
Project-URL: Repository, https://github.com/KnowOneActual/mail-ops-scripts
Classifier: Programming Language :: Python :: 3
Classifier: Operating System :: OS Independent
Requires-Python: >=3.8
License-File: LICENSE
Provides-Extra: dev
Requires-Dist: pytest>=7.0; extra == "dev"
Requires-Dist: black>=23.0; extra == "dev"
Requires-Dist: isort>=5.12; extra == "dev"
Requires-Dist: mypy>=1.5; extra == "dev"
Requires-Dist: build; extra == "dev"
Requires-Dist: twine; extra == "dev"
Dynamic: license-file
